setup.py
lib/tuisongbao/__init__.py
lib/tuisongbao/client.py
lib/tuisongbao/utils.py
lib/tuisongbao.egg-info/PKG-INFO
lib/tuisongbao.egg-info/SOURCES.txt
lib/tuisongbao.egg-info/dependency_links.txt
lib/tuisongbao.egg-info/requires.txt
lib/tuisongbao.egg-info/top_level.txt