Metadata-Version: 1.0
Name: tuisongbao
Version: 0.9.0
Summary: Tuisongbao SDK
Home-page: https://github.com/tuisongbao/python-sdk
Author: www.tuisongbao.com
Author-email: support@tuisongbao.com
License: Apache
Platform: UNKNOWN
